labcas/workflow/__init__.py
labcas/workflow/dags/__init__.py
labcas/workflow/manager/__init__.py
labcas/workflow/manager/datastore.py
labcas/workflow/manager/main.py
labcas/workflow/manager/process_collection.py
labcas/workflow/steps/__init__.py
labcas/workflow/steps/alphan/process.py
labcas/workflow/steps/alphan/utils.py
labcas/workflow/steps/alphan/models/unet_128.raw/keras_metadata.pb
labcas/workflow/steps/alphan/models/unet_128.raw/saved_model.pb
labcas/workflow/steps/alphan/models/unet_128.raw/variables/variables.data-00000-of-00001
labcas/workflow/steps/alphan/models/unet_128.raw/variables/variables.index
labcas/workflow/steps/alphan/models/unet_256.raw/keras_metadata.pb
labcas/workflow/steps/alphan/models/unet_256.raw/saved_model.pb
labcas/workflow/steps/alphan/models/unet_256.raw/variables/variables.data-00000-of-00001
labcas/workflow/steps/alphan/models/unet_256.raw/variables/variables.index
labcas/workflow/steps/alphan/models/unet_64.raw/keras_metadata.pb
labcas/workflow/steps/alphan/models/unet_64.raw/saved_model.pb
labcas/workflow/steps/alphan/models/unet_64.raw/variables/variables.data-00000-of-00001
labcas/workflow/steps/alphan/models/unet_64.raw/variables/variables.index
labcas_workflow-0.1.13.dist-info/METADATA
labcas_workflow-0.1.13.dist-info/WHEEL
labcas_workflow-0.1.13.dist-info/entry_points.txt
labcas_workflow-0.1.13.dist-info/top_level.txt
labcas_workflow-0.1.13.dist-info/zip-safe
labcas_workflow-0.1.13.dist-info/RECORD
