Metadata-Version: 2.4
Name: labcas.workflow
Version: 0.1.13
Summary: Get Planetary Data from the Planetary Data System (PDS)
Home-page: https://github.com/NASA-PDS/peppi
Download-URL: https://github.com/NASA-PDS/peppi/releases/
Author: Labcas
Author-email: labcas@jpl.nasa.gov
License: apache-2.0
Keywords: pds,planetary data,api
Classifier: Programming Language :: Python :: 3
Classifier: Programming Language :: Python :: 3.9
Classifier: License :: OSI Approved :: Apache Software License
Classifier: Operating System :: OS Independent
Requires-Python: >=3.11
Requires-Dist: numpy~=1.24.3
Requires-Dist: scikit-image~=0.24.0
Requires-Dist: pandas~=2.2.3
Requires-Dist: matplotlib~=3.9.4
Requires-Dist: boto3==1.35.16
Requires-Dist: dask~=2024.8.0
Requires-Dist: distributed~=2024.8.0
Provides-Extra: ml-worker
Requires-Dist: tensorflow~=2.12.1; extra == "ml-worker"
Provides-Extra: dev
Requires-Dist: black~=25.1.0; extra == "dev"
Requires-Dist: flake8~=7.2.0; extra == "dev"
Requires-Dist: flake8-bugbear~=24.12.12; extra == "dev"
Requires-Dist: flake8-docstrings~=1.7.0; extra == "dev"
Requires-Dist: pep8-naming~=0.14.1; extra == "dev"
Requires-Dist: mypy~=1.15.0; extra == "dev"
Requires-Dist: pydocstyle~=6.3.0; extra == "dev"
Requires-Dist: coverage~=7.8.0; extra == "dev"
Requires-Dist: pytest~=8.3.5; extra == "dev"
Requires-Dist: pytest-cov~=6.1.1; extra == "dev"
Requires-Dist: pytest-watch~=4.2.0; extra == "dev"
Requires-Dist: pytest-xdist~=3.6.1; extra == "dev"
Requires-Dist: pre-commit~=4.2.0; extra == "dev"
Requires-Dist: sphinx~=8.2.3; extra == "dev"
Requires-Dist: sphinx-rtd-theme~=3.0.2; extra == "dev"
Requires-Dist: tox~=4.25.0; extra == "dev"
Requires-Dist: types-setuptools~=78.1.0.20250329; extra == "dev"
Requires-Dist: Jinja2~=3.1.6; extra == "dev"
Requires-Dist: docutils~=0.21.2; extra == "dev"
Dynamic: download-url
